dogbin/__init__.py
dogbin/dogbin.py
dogbin-0.1.dist-info/LICENSE
dogbin-0.1.dist-info/METADATA
dogbin-0.1.dist-info/WHEEL
dogbin-0.1.dist-info/top_level.txt
dogbin-0.1.dist-info/RECORD
