Metadata-Version: 2.1
Name: dogbin
Version: 0.1
Summary: Dogbin API Wrapper
Home-page: https://github.com/Deleted-accounts/Dogbin-API-Wrapper
Author: DeletedAccounts
Author-email: deletedaccuonts@hi2.in
License: GNU Lesser General Public License v3 (LGPLv3)
Project-URL: Bug Tracker, https://github.com/Deleted-accounts/Dogbin-API-Wrapper/issues
Platform: UNKNOWN
Classifier: Development Status :: 3 - Alpha
Classifier: Programming Language :: Python :: 3.9
Requires-Python: >=3.7
Requires-Dist: aiohttp (==3.7.4.post0)
Requires-Dist: requests (==2.25.1)
